meggie_simpleplugin/__init__.py
meggie_simpleplugin/configuration.json
meggie_simpleplugin/actions/__init__.py
meggie_simpleplugin/actions/hello/__init__.py
meggie_simpleplugin/actions/hello/configuration.json
meggie_simpleplugin/actions/hello/tests/__init__.py
meggie_simpleplugin/actions/hello/tests/test_hello.py
meggie_simpleplugin-0.2.2.dist-info/METADATA
meggie_simpleplugin-0.2.2.dist-info/WHEEL
meggie_simpleplugin-0.2.2.dist-info/top_level.txt
meggie_simpleplugin-0.2.2.dist-info/RECORD
